{
    "board": [
        {
            "fname": "Bob",
            "lname": "Kruzel",
            "position": "President"
        },{
            "fname": "Katie",
            "lname": "Jones",
            "position": "Vice President"
        },{
            "fname": "Megan",
            "lname": "Perkins",
            "position": "Treasurer"
        },{
            "fname": "Karen",
            "lname": "Spencer",
            "position": "Secretary"
        },{
            "fname": "Jenny",
            "lname": "Lofthus",
            "position": "Member At Large"
        }
    ],
    "chairs": [
        {
            "fname": "Liz",
            "lname": "Ballew",
            "position": "Volunteer Chair"
        },{
            "fname": "Angelica",
            "lname": "Ortiz",
            "position": "Spirit Wear"
        },{
            "fname": "Holly",
            "lname": "Egan",
            "position": "Dive Representative"
        },{
            "fname": "Open",
            "lname": " ",
            "position": "Meet Meals"
        },{
            "fname": "Sara",
            "lname": "Harshbarger",
            "position": "Banquet Chair"
        },{
            "fname": "Kayde",
            "lname": "Weiland",
            "position": "Senior Night Chair"
        }
    ]
}